rsp_jupyter_extensions/__init__.py
rsp_jupyter_extensions/_version.py
rsp_jupyter_extensions/handlers/__init__.py
rsp_jupyter_extensions/handlers/_utils.py
rsp_jupyter_extensions/handlers/environment.py
rsp_jupyter_extensions/handlers/execution.py
rsp_jupyter_extensions/handlers/ghostwriter.py
rsp_jupyter_extensions/handlers/hub.py
rsp_jupyter_extensions/handlers/pdfexport.py
rsp_jupyter_extensions/handlers/query.py
rsp_jupyter_extensions/handlers/tutorials.py
rsp_jupyter_extensions/models/__init__.py
rsp_jupyter_extensions/models/query.py
rsp_jupyter_extensions/models/tutorials.py
rsp_jupyter_extensions/tests/__init__.py
rsp_jupyter_extensions/tests/copy_test.py
rsp_jupyter_extensions/tests/execution_test.py
rsp_jupyter_extensions/tests/export_test.py
rsp_jupyter_extensions/tests/handlers_test.py
rsp_jupyter_extensions/tests/hierarchy_test.py
rsp_jupyter_extensions/tests/test_handlers.py
rsp_jupyter_extensions/tests/data/nb.ipynb
rsp_jupyter_extensions/tests/data/pandoc
rsp_jupyter_extensions/tests/data/typst
rsp_jupyter_extensions-0.19.3.data/data/etc/jupyter/jupyter_server_config.d/rsp_jupyter_extensions.json
rsp_jupyter_extensions-0.19.3.data/data/share/jupyter/labextensions/rsp-jupyter-extensions/package.json
rsp_jupyter_extensions-0.19.3.data/data/share/jupyter/labextensions/rsp-jupyter-extensions/static/404.327b3251fc5d2b2c9194.js
rsp_jupyter_extensions-0.19.3.data/data/share/jupyter/labextensions/rsp-jupyter-extensions/static/696.fc4612ca04e5bf6a0138.js
rsp_jupyter_extensions-0.19.3.data/data/share/jupyter/labextensions/rsp-jupyter-extensions/static/728.3f7cf28eb39c025f6c66.js
rsp_jupyter_extensions-0.19.3.data/data/share/jupyter/labextensions/rsp-jupyter-extensions/static/remoteEntry.3adf681d4a282c9dabab.js
rsp_jupyter_extensions-0.19.3.data/data/share/jupyter/labextensions/rsp-jupyter-extensions/static/style.js
rsp_jupyter_extensions-0.19.3.data/data/share/jupyter/labextensions/rsp-jupyter-extensions/static/third-party-licenses.json
rsp_jupyter_extensions-0.19.3.dist-info/METADATA
rsp_jupyter_extensions-0.19.3.dist-info/WHEEL
rsp_jupyter_extensions-0.19.3.dist-info/licenses/LICENSE
rsp_jupyter_extensions-0.19.3.dist-info/RECORD
