Metadata-Version: 2.4
Name: rsp_jupyter_extensions
Version: 0.19.3
Dynamic: Keywords
Summary: Jupyter Extensions for the Rubin Science Platform
Project-URL: Homepage, https://github.com/lsst-sqre/rsp-jupyter-extensions 
Project-URL: Bug Tracker, https://github.com/lsst-sqre/rsp-jupyter-extensions /issues
Project-URL: Repository, https://github.com/lsst-sqre/rsp-jupyter-extensions .git
Author-email: Adam Thornton <athornton@lsst.org>
License: MIT License
License-File: LICENSE
Classifier: Framework :: Jupyter
Classifier: Framework :: Jupyter :: JupyterLab
Classifier: Framework :: Jupyter :: JupyterLab :: 4
Classifier: Framework :: Jupyter :: JupyterLab :: Extensions
Classifier: Framework :: Jupyter :: JupyterLab :: Extensions :: Prebuilt
Classifier: License :: OSI Approved :: BSD License
Classifier: Programming Language :: Python
Classifier: Programming Language :: Python :: 3
Classifier: Programming Language :: Python :: 3.12
Classifier: Programming Language :: Python :: 3.13
Classifier: Programming Language :: Python :: 3.14
Requires-Python: >=3.12
Requires-Dist: httpx
Requires-Dist: jinja2
Requires-Dist: jupyter-server<3,>=2.0.1
Requires-Dist: lsst-rsp>=0.10.1
Requires-Dist: pydantic
Requires-Dist: requests
Requires-Dist: xmltodict
Provides-Extra: test
Requires-Dist: coverage; extra == 'test'
Requires-Dist: mypy; extra == 'test'
Requires-Dist: pre-commit; extra == 'test'
Requires-Dist: pytest; extra == 'test'
Requires-Dist: pytest-asyncio; extra == 'test'
Requires-Dist: pytest-cov; extra == 'test'
Requires-Dist: pytest-jupyter[server]>=0.6.0; extra == 'test'
Requires-Dist: ruff; extra == 'test'
Requires-Dist: types-requests; extra == 'test'
Requires-Dist: types-xmltodict; extra == 'test'
